{
    "_links": {
        "self": {
            "href": "https:\/\/8080-francis13cr-proyectofin-7gg39c0j798.ws-us100.gitpod.io\/node\/17?_format=hal_json"
        },
        "type": {
            "href": "https:\/\/8080-francis13cr-proyectofin-7gg39c0j798.ws-us100.gitpod.io\/rest\/type\/node\/post"
        },
        "https:\/\/8080-francis13cr-proyectofin-7gg39c0j798.ws-us100.gitpod.io\/rest\/relation\/node\/post\/revision_uid": [
            {
                "href": "https:\/\/8080-francis13cr-proyectofin-7gg39c0j798.ws-us100.gitpod.io\/user\/0?_format=hal_json"
            }
        ],
        "https:\/\/8080-francis13cr-proyectofin-7gg39c0j798.ws-us100.gitpod.io\/rest\/relation\/node\/post\/uid": [
            {
                "href": "https:\/\/8080-francis13cr-proyectofin-7gg39c0j798.ws-us100.gitpod.io\/user\/0?_format=hal_json",
                "lang": "en"
            }
        ],
        "https:\/\/8080-francis13cr-proyectofin-7gg39c0j798.ws-us100.gitpod.io\/rest\/relation\/node\/post\/field_category": [
            {
                "href": "https:\/\/8080-francis13cr-proyectofin-7gg39c0j798.ws-us100.gitpod.io\/taxonomy\/term\/17?_format=hal_json"
            }
        ],
        "https:\/\/8080-francis13cr-proyectofin-7gg39c0j798.ws-us100.gitpod.io\/rest\/relation\/node\/post\/field_image": [
            {
                "href": "https:\/\/8080-francis13cr-proyectofin-7gg39c0j798.ws-us100.gitpod.io\/sites\/default\/files\/2023-06\/ipad.png",
                "lang": "en"
            }
        ],
        "https:\/\/8080-francis13cr-proyectofin-7gg39c0j798.ws-us100.gitpod.io\/rest\/relation\/node\/post\/field_keywords": [
            {
                "href": "https:\/\/8080-francis13cr-proyectofin-7gg39c0j798.ws-us100.gitpod.io\/taxonomy\/term\/11?_format=hal_json"
            }
        ]
    },
    "nid": [
        {
            "value": 17
        }
    ],
    "uuid": [
        {
            "value": "dde3139a-2a14-4e29-aa21-2ad0b554c0b7"
        }
    ],
    "langcode": [
        {
            "value": "en",
            "lang": "en"
        }
    ],
    "type": [
        {
            "target_id": "post"
        }
    ],
    "revision_timestamp": [
        {
            "value": "2023-06-20T20:57:34+00:00",
            "format": "Y-m-d\\TH:i:sP"
        }
    ],
    "_embedded": {
        "https:\/\/8080-francis13cr-proyectofin-7gg39c0j798.ws-us100.gitpod.io\/rest\/relation\/node\/post\/revision_uid": [
            {
                "_links": {
                    "self": {
                        "href": "https:\/\/8080-francis13cr-proyectofin-7gg39c0j798.ws-us100.gitpod.io\/user\/0?_format=hal_json"
                    },
                    "type": {
                        "href": "https:\/\/8080-francis13cr-proyectofin-7gg39c0j798.ws-us100.gitpod.io\/rest\/type\/user\/user"
                    }
                },
                "uuid": [
                    {
                        "value": "88b135ba-1b5e-4ca2-934b-ab8fb7724d7d"
                    }
                ]
            }
        ],
        "https:\/\/8080-francis13cr-proyectofin-7gg39c0j798.ws-us100.gitpod.io\/rest\/relation\/node\/post\/uid": [
            {
                "_links": {
                    "self": {
                        "href": "https:\/\/8080-francis13cr-proyectofin-7gg39c0j798.ws-us100.gitpod.io\/user\/0?_format=hal_json"
                    },
                    "type": {
                        "href": "https:\/\/8080-francis13cr-proyectofin-7gg39c0j798.ws-us100.gitpod.io\/rest\/type\/user\/user"
                    }
                },
                "uuid": [
                    {
                        "value": "88b135ba-1b5e-4ca2-934b-ab8fb7724d7d"
                    }
                ],
                "lang": "en"
            }
        ],
        "https:\/\/8080-francis13cr-proyectofin-7gg39c0j798.ws-us100.gitpod.io\/rest\/relation\/node\/post\/field_category": [
            {
                "_links": {
                    "self": {
                        "href": "https:\/\/8080-francis13cr-proyectofin-7gg39c0j798.ws-us100.gitpod.io\/taxonomy\/term\/17?_format=hal_json"
                    },
                    "type": {
                        "href": "https:\/\/8080-francis13cr-proyectofin-7gg39c0j798.ws-us100.gitpod.io\/rest\/type\/taxonomy_term\/categoria"
                    }
                },
                "uuid": [
                    {
                        "value": "01110b9b-5036-4801-b996-002f989a8a39"
                    }
                ]
            }
        ],
        "https:\/\/8080-francis13cr-proyectofin-7gg39c0j798.ws-us100.gitpod.io\/rest\/relation\/node\/post\/field_image": [
            {
                "_links": {
                    "self": {
                        "href": "https:\/\/8080-francis13cr-proyectofin-7gg39c0j798.ws-us100.gitpod.io\/sites\/default\/files\/2023-06\/ipad.png"
                    },
                    "type": {
                        "href": "https:\/\/8080-francis13cr-proyectofin-7gg39c0j798.ws-us100.gitpod.io\/rest\/type\/file\/file"
                    }
                },
                "uuid": [
                    {
                        "value": "33a0e8a1-44e9-4c8f-90df-6d94fd5446ed"
                    }
                ],
                "lang": "en"
            }
        ],
        "https:\/\/8080-francis13cr-proyectofin-7gg39c0j798.ws-us100.gitpod.io\/rest\/relation\/node\/post\/field_keywords": [
            {
                "_links": {
                    "self": {
                        "href": "https:\/\/8080-francis13cr-proyectofin-7gg39c0j798.ws-us100.gitpod.io\/taxonomy\/term\/11?_format=hal_json"
                    },
                    "type": {
                        "href": "https:\/\/8080-francis13cr-proyectofin-7gg39c0j798.ws-us100.gitpod.io\/rest\/type\/taxonomy_term\/palabras_clave"
                    }
                },
                "uuid": [
                    {
                        "value": "8465c947-e26f-4d2e-8892-f3d67c9584ad"
                    }
                ]
            }
        ]
    },
    "status": [
        {
            "value": true,
            "lang": "en"
        }
    ],
    "title": [
        {
            "value": "Meus",
            "lang": "en"
        }
    ],
    "created": [
        {
            "value": "2023-05-30T00:06:01+00:00",
            "lang": "en",
            "format": "Y-m-d\\TH:i:sP"
        }
    ],
    "changed": [
        {
            "value": "2023-06-26T00:21:21+00:00",
            "lang": "en",
            "format": "Y-m-d\\TH:i:sP"
        }
    ],
    "promote": [
        {
            "value": false,
            "lang": "en"
        }
    ],
    "sticky": [
        {
            "value": false,
            "lang": "en"
        }
    ],
    "default_langcode": [
        {
            "value": true,
            "lang": "en"
        }
    ],
    "revision_translation_affected": [
        {
            "value": true,
            "lang": "en"
        }
    ],
    "path": [
        {
            "alias": null,
            "pid": null,
            "langcode": "en",
            "lang": "en"
        }
    ],
    "body": [
        {
            "value": "Accumsan gemino inhibeo jumentum mauris nulla. At comis distineo nutus torqueo vulpes. Camur eligo jumentum quidne scisco. Dignissim imputo pertineo quidem quis si suscipit tincidunt usitas uxor. Nobis quidem si virtus vulputate.\r\n\r\nFacilisi illum imputo magna pneum quae quidem quidne validus vulpes. Ex rusticus sagaciter tum velit. Enim nulla si uxor. Ex occuro quidne uxor valetudo. Abluo adipiscing blandit patria quidem sudo typicus. Accumsan comis quadrum quae. Dolore eum iaceo interdico nulla premo secundum tincidunt vindico. Immitto meus vicis voco. Antehabeo erat exputo.\r\n\r\nAmet antehabeo consectetuer facilisi hos jumentum sagaciter saluto zelus. Aliquam eu mauris natu paratus plaga tego. Capto dignissim scisco. Cui meus pagus. Brevitas ideo nisl paratus singularis verto vulpes. Duis luctus utinam vel vereor. Aliquam fere obruo populus validus. At ex gilvus qui tego. Autem commoveo cui eu pagus persto quadrum quia tincidunt vulpes. Ex pecus persto ratis refoveo si validus venio volutpat ymo.\r\n\r\nAccumsan antehabeo bene blandit exputo iustum saluto similis suscipit. Adipiscing bene humo inhibeo loquor luctus quidem secundum si suscipere. Adipiscing consectetuer eu jugis luctus neo pala quia ullamcorper uxor. Iustum lenis roto. Aliquip esca quidne tincidunt valde. Damnum facilisi fere hos magna quidne si venio.\r\n\r\nLobortis mauris pagus pecus pneum populus premo. Abdo autem damnum facilisis gilvus illum iustum te ullamcorper. Dignissim gravis in metuo refoveo. Lenis metuo saepius. Dignissim humo interdico typicus. Neo neque valde. Abico camur immitto iusto iustum os utrum vel vicis. Adipiscing blandit camur conventio importunus quia quibus. Exputo humo ludus olim os refoveo si wisi.\r\n\r\nCommodo decet humo in inhibeo iusto quadrum suscipit utinam. Appellatio augue consequat esca immitto sino. Humo nimis venio. Commoveo dolus ibidem ludus meus patria refero suscipit valetudo velit. Abico appellatio autem damnum ibidem vereor vicis wisi.\r\n\r\nInterdico loquor ratis wisi. Cui eligo elit enim gemino iriure iustum sit torqueo. Augue ea elit iustum mauris volutpat. Aptent caecus et iriure populus. Amet bene dignissim pala. Abluo amet appellatio defui praesent premo tum validus vulpes. Amet facilisis macto quidem vindico.\r\n\r\nAmet consectetuer exerci genitus inhibeo refero. Adipiscing cogo molior veniam. Abdo eros olim saluto similis. Abico ex ideo jus scisco valde. Enim gilvus lenis persto sino torqueo validus venio voco.\r\n\r\nEx quidne refero sudo vicis. Camur exputo ludus natu paulatim secundum similis tego velit zelus. Eligo esse iaceo ille inhibeo lobortis nibh quadrum vero. Dolore erat et ullamcorper ut velit. Ad genitus mauris nulla nunc pecus plaga torqueo. Aptent ex exputo jus luptatum nulla premo similis vicis. Capto consequat hendrerit mos os pneum secundum uxor.\r\n\r\nHumo iaceo ille si. Abluo elit esse et exputo magna praesent si singularis ullamcorper. Ille imputo jus metuo quidem wisi. Abluo euismod iustum nunc obruo pertineo ulciscor zelus.\r\n\r\nIaceo quis roto ullamcorper utinam. Bene oppeto sudo vel virtus. Imputo jus luptatum quidne sed si singularis. Genitus incassum scisco velit. Consectetuer cui gilvus meus minim obruo quibus tum vero. Ea natu olim refero rusticus similis singularis tation usitas venio. Adipiscing augue esca feugiat illum magna plaga populus vicis. Abdo eligo metuo sed torqueo ymo.\r\n\r\nCommoveo ex iustum secundum tincidunt. Acsi metuo utinam. Ex humo inhibeo iusto occuro pagus quadrum quae secundum ut. Damnum exerci lobortis scisco sit tamen tum. Dolor exputo in paulatim.\r\n\r\n",
            "format": "plain_text",
            "processed": "<p>Accumsan gemino inhibeo jumentum mauris nulla. At comis distineo nutus torqueo vulpes. Camur eligo jumentum quidne scisco. Dignissim imputo pertineo quidem quis si suscipit tincidunt usitas uxor. Nobis quidem si virtus vulputate.<\/p>\n<p>Facilisi illum imputo magna pneum quae quidem quidne validus vulpes. Ex rusticus sagaciter tum velit. Enim nulla si uxor. Ex occuro quidne uxor valetudo. Abluo adipiscing blandit patria quidem sudo typicus. Accumsan comis quadrum quae. Dolore eum iaceo interdico nulla premo secundum tincidunt vindico. Immitto meus vicis voco. Antehabeo erat exputo.<\/p>\n<p>Amet antehabeo consectetuer facilisi hos jumentum sagaciter saluto zelus. Aliquam eu mauris natu paratus plaga tego. Capto dignissim scisco. Cui meus pagus. Brevitas ideo nisl paratus singularis verto vulpes. Duis luctus utinam vel vereor. Aliquam fere obruo populus validus. At ex gilvus qui tego. Autem commoveo cui eu pagus persto quadrum quia tincidunt vulpes. Ex pecus persto ratis refoveo si validus venio volutpat ymo.<\/p>\n<p>Accumsan antehabeo bene blandit exputo iustum saluto similis suscipit. Adipiscing bene humo inhibeo loquor luctus quidem secundum si suscipere. Adipiscing consectetuer eu jugis luctus neo pala quia ullamcorper uxor. Iustum lenis roto. Aliquip esca quidne tincidunt valde. Damnum facilisi fere hos magna quidne si venio.<\/p>\n<p>Lobortis mauris pagus pecus pneum populus premo. Abdo autem damnum facilisis gilvus illum iustum te ullamcorper. Dignissim gravis in metuo refoveo. Lenis metuo saepius. Dignissim humo interdico typicus. Neo neque valde. Abico camur immitto iusto iustum os utrum vel vicis. Adipiscing blandit camur conventio importunus quia quibus. Exputo humo ludus olim os refoveo si wisi.<\/p>\n<p>Commodo decet humo in inhibeo iusto quadrum suscipit utinam. Appellatio augue consequat esca immitto sino. Humo nimis venio. Commoveo dolus ibidem ludus meus patria refero suscipit valetudo velit. Abico appellatio autem damnum ibidem vereor vicis wisi.<\/p>\n<p>Interdico loquor ratis wisi. Cui eligo elit enim gemino iriure iustum sit torqueo. Augue ea elit iustum mauris volutpat. Aptent caecus et iriure populus. Amet bene dignissim pala. Abluo amet appellatio defui praesent premo tum validus vulpes. Amet facilisis macto quidem vindico.<\/p>\n<p>Amet consectetuer exerci genitus inhibeo refero. Adipiscing cogo molior veniam. Abdo eros olim saluto similis. Abico ex ideo jus scisco valde. Enim gilvus lenis persto sino torqueo validus venio voco.<\/p>\n<p>Ex quidne refero sudo vicis. Camur exputo ludus natu paulatim secundum similis tego velit zelus. Eligo esse iaceo ille inhibeo lobortis nibh quadrum vero. Dolore erat et ullamcorper ut velit. Ad genitus mauris nulla nunc pecus plaga torqueo. Aptent ex exputo jus luptatum nulla premo similis vicis. Capto consequat hendrerit mos os pneum secundum uxor.<\/p>\n<p>Humo iaceo ille si. Abluo elit esse et exputo magna praesent si singularis ullamcorper. Ille imputo jus metuo quidem wisi. Abluo euismod iustum nunc obruo pertineo ulciscor zelus.<\/p>\n<p>Iaceo quis roto ullamcorper utinam. Bene oppeto sudo vel virtus. Imputo jus luptatum quidne sed si singularis. Genitus incassum scisco velit. Consectetuer cui gilvus meus minim obruo quibus tum vero. Ea natu olim refero rusticus similis singularis tation usitas venio. Adipiscing augue esca feugiat illum magna plaga populus vicis. Abdo eligo metuo sed torqueo ymo.<\/p>\n<p>Commoveo ex iustum secundum tincidunt. Acsi metuo utinam. Ex humo inhibeo iusto occuro pagus quadrum quae secundum ut. Damnum exerci lobortis scisco sit tamen tum. Dolor exputo in paulatim.<\/p>\n",
            "summary": "Accumsan gemino inhibeo jumentum mauris nulla. At comis distineo nutus torqueo vulpes. Camur eligo jumentum quidne scisco. Dignissim imputo pertineo quidem quis si suscipit tincidunt usitas uxor. Nobis quidem si virtus vulputate.\r\n\r\nFacilisi illum imputo magna pneum quae quidem quidne validus vulpes. Ex rusticus sagaciter tum velit. Enim nulla si uxor. Ex occuro quidne uxor valetudo. Abluo adipiscing blandit patria quidem sudo typicus. Accumsan comis quadrum quae. Dolore eum iaceo interdico nulla premo secundum tincidunt vindico. Immitto meus vicis voco. Antehabeo erat exputo.\r\n\r\nAmet antehabeo consectetuer facilisi hos jumentum sagaciter saluto zelus. Aliquam eu mauris natu paratus plaga tego. Capto dignissim scisco. Cui meus pagus. Brevitas ideo nisl paratus singularis verto vulpes. Duis luctus utinam vel vereor. Aliquam fere obruo populus validus. At ex gilvus qui tego. Autem commoveo cui eu pagus persto quadrum quia tincidunt vulpes. Ex pecus persto ratis refoveo si validus venio volutpat ymo.\r\n\r\nAccumsan antehabeo bene blandit exputo iustum saluto similis suscipit. Adipiscing bene humo inhibeo loquor luctus quidem secundum si suscipere. Adipiscing consectetuer eu jugis luctus neo pala quia ullamcorper uxor. Iustum lenis roto. Aliquip esca quidne tincidunt valde. Damnum facilisi fere hos magna quidne si venio.\r\n\r\nLobortis mauris pagus pecus pneum populus premo. Abdo autem damnum facilisis gilvus illum iustum te ullamcorper. Dignissim gravis in metuo refoveo. Lenis metuo saepius. Dignissim humo interdico typicus. Neo neque valde. Abico camur immitto iusto iustum os utrum vel vicis. Adipiscing blandit camur conventio importunus quia quibus. Exputo humo ludus olim os refoveo si wisi.\r\n\r\nCommodo decet humo in inhibeo iusto quadrum suscipit utinam. Appellatio augue consequat esca immitto sino. Humo nimis venio. Commoveo dolus ibidem ludus meus patria refero suscipit valetudo velit. Abico appellatio autem damnum ibidem vereor vicis wisi.\r\n\r\nInterdico loquor ratis wisi. Cui eligo elit enim gemino iriure iustum sit torqueo. Augue ea elit iustum mauris volutpat. Aptent caecus et iriure populus. Amet bene dignissim pala. Abluo amet appellatio defui praesent premo tum validus vulpes. Amet facilisis macto quidem vindico.\r\n\r\nAmet consectetuer exerci genitus inhibeo refero. Adipiscing cogo molior veniam. Abdo eros olim saluto similis. Abico ex ideo jus scisco valde. Enim gilvus lenis persto sino torqueo validus venio voco.\r\n\r\nEx quidne refero sudo vicis. Camur exputo ludus natu paulatim secundum similis tego velit zelus. Eligo esse iaceo ille inhibeo lobortis nibh quadrum vero. Dolore erat et ullamcorper ut velit. Ad genitus mauris nulla nunc pecus plaga torqueo. Aptent ex exputo jus luptatum nulla premo similis vicis. Capto consequat hendrerit mos os pneum secundum uxor.\r\n\r\nHumo iaceo ille si. Abluo elit esse et exputo magna praesent si singularis ullamcorper. Ille imputo jus metuo quidem wisi. Abluo euismod iustum nunc obruo pertineo ulciscor zelus.\r\n\r\nIaceo quis roto ullamcorper utinam. Bene oppeto sudo vel virtus. Imputo jus luptatum quidne sed si singularis. Genitus incassum scisco velit. Consectetuer cui gilvus meus minim obruo quibus tum vero. Ea natu olim refero rusticus similis singularis tation usitas venio. Adipiscing augue esca feugiat illum magna plaga populus vicis. Abdo eligo metuo sed torqueo ymo.\r\n\r\nCommoveo ex iustum secundum tincidunt. Acsi metuo utinam. Ex humo inhibeo iusto occuro pagus quadrum quae secundum ut. Damnum exerci lobortis scisco sit tamen tum. Dolor exputo in paulatim.\r\n\r\n",
            "lang": "en"
        }
    ],
    "field_comentarios": [
        {
            "status": 2,
            "cid": 0,
            "last_comment_timestamp": 1687294654,
            "last_comment_name": null,
            "last_comment_uid": 0,
            "comment_count": 0
        }
    ],
    "field_re": [
        {
            "uri": "http:\/\/www.phetricl.info",
            "title": "",
            "options": []
        },
        {
            "uri": "http:\/\/www.surivitresohu.edu",
            "title": "",
            "options": []
        },
        {
            "uri": "http:\/\/www.wrihoswa.biz",
            "title": "Aliquip comis defui facilisis magna oppeto ratis virtus.",
            "options": []
        }
    ]
}