{
    "_links": {
        "self": {
            "href": "https:\/\/8080-francis13cr-proyectofin-sscwnjz0rse.ws-us100.gitpod.io\/sites\/default\/files\/2023-06\/OIP.jpg"
        },
        "type": {
            "href": "https:\/\/8080-francis13cr-proyectofin-sscwnjz0rse.ws-us100.gitpod.io\/rest\/type\/file\/file"
        }
    },
    "fid": [
        {
            "value": 24
        }
    ],
    "uuid": [
        {
            "value": "9928489e-484b-42ed-8aae-22315d800efe"
        }
    ],
    "langcode": [
        {
            "value": "en"
        }
    ],
    "filename": [
        {
            "value": "OIP.jpg"
        }
    ],
    "uri": [
        {
            "value": "public:\/\/2023-06\/OIP.jpg",
            "url": "\/sites\/default\/files\/2023-06\/OIP.jpg"
        }
    ],
    "filemime": [
        {
            "value": "image\/jpeg"
        }
    ],
    "filesize": [
        {
            "value": 9341
        }
    ],
    "status": [
        {
            "value": true
        }
    ],
    "created": [
        {
            "value": "2023-06-21T02:44:24+00:00",
            "format": "Y-m-d\\TH:i:sP"
        }
    ],
    "changed": [
        {
            "value": "2023-06-21T02:44:37+00:00",
            "format": "Y-m-d\\TH:i:sP"
        }
    ]
}