{
    "_links": {
        "self": {
            "href": "https:\/\/8080-francis13cr-proyectofin-7gg39c0j798.ws-us101.gitpod.io\/sites\/default\/files\/inline-images\/photo1687741067.jpeg"
        },
        "type": {
            "href": "https:\/\/8080-francis13cr-proyectofin-7gg39c0j798.ws-us101.gitpod.io\/rest\/type\/file\/file"
        },
        "https:\/\/8080-francis13cr-proyectofin-7gg39c0j798.ws-us101.gitpod.io\/rest\/relation\/file\/file\/uid": [
            {
                "href": "https:\/\/8080-francis13cr-proyectofin-7gg39c0j798.ws-us101.gitpod.io\/user\/1?_format=hal_json"
            }
        ]
    },
    "fid": [
        {
            "value": 34
        }
    ],
    "uuid": [
        {
            "value": "d182fd3c-cdc4-466e-ba40-bc7bd8c25a5a"
        }
    ],
    "langcode": [
        {
            "value": "en"
        }
    ],
    "_embedded": {
        "https:\/\/8080-francis13cr-proyectofin-7gg39c0j798.ws-us101.gitpod.io\/rest\/relation\/file\/file\/uid": [
            {
                "_links": {
                    "self": {
                        "href": "https:\/\/8080-francis13cr-proyectofin-7gg39c0j798.ws-us101.gitpod.io\/user\/1?_format=hal_json"
                    },
                    "type": {
                        "href": "https:\/\/8080-francis13cr-proyectofin-7gg39c0j798.ws-us101.gitpod.io\/rest\/type\/user\/user"
                    }
                },
                "uuid": [
                    {
                        "value": "3360b810-2e24-4a58-99a4-309c9249a160"
                    }
                ]
            }
        ]
    },
    "filename": [
        {
            "value": "photo1687741067.jpeg"
        }
    ],
    "uri": [
        {
            "value": "public:\/\/inline-images\/photo1687741067.jpeg",
            "url": "\/sites\/default\/files\/inline-images\/photo1687741067.jpeg"
        }
    ],
    "filemime": [
        {
            "value": "image\/jpeg"
        }
    ],
    "filesize": [
        {
            "value": 128866
        }
    ],
    "status": [
        {
            "value": true
        }
    ],
    "created": [
        {
            "value": "2023-06-26T01:02:48+00:00",
            "format": "Y-m-d\\TH:i:sP"
        }
    ],
    "changed": [
        {
            "value": "2023-06-26T01:03:29+00:00",
            "format": "Y-m-d\\TH:i:sP"
        }
    ]
}